piqs/__init__.py
piqs/about.py
piqs/cite.py
piqs/dicke.py
piqs/cy/__init__.py
piqs/cy/dicke.cpp
piqs/cy/dicke.cpython-36m-darwin.so
piqs/cy/dicke.pyx
piqs/tests/__init__.py
piqs/tests/test_dicke.py
piqs-1.2.0.dist-info/METADATA
piqs-1.2.0.dist-info/RECORD
piqs-1.2.0.dist-info/WHEEL
piqs-1.2.0.dist-info/top_level.txt
